rjmespath-0.2.6.dist-info/METADATA
rjmespath-0.2.6.dist-info/WHEEL
rjmespath/__init__.py
rjmespath/__init__.pyi
rjmespath/py.typed
rjmespath/rjmespath.abi3.so
rjmespath-0.2.6.dist-info/RECORD
