Metadata-Version: 2.1
Name: rjmespath
Version: 0.2.6
Summary: jmespath.rs Python binding
Author: messense <messense@icloud.com>
Author-email: messense <messense@icloud.com>
License: MIT
Project-URL: Source Code, https://github.com/messense/rjmespath-py
